CHANGES.rst
MANIFEST.in
README.rst
TODO.txt
setup.cfg
setup.py
Products/__init__.py
Products.feedfeeder.egg-info/PKG-INFO
Products.feedfeeder.egg-info/SOURCES.txt
Products.feedfeeder.egg-info/dependency_links.txt
Products.feedfeeder.egg-info/entry_points.txt
Products.feedfeeder.egg-info/namespace_packages.txt
Products.feedfeeder.egg-info/not-zip-safe
Products.feedfeeder.egg-info/requires.txt
Products.feedfeeder.egg-info/top_level.txt
Products/feedfeeder/__init__.py
Products/feedfeeder/config.py
Products/feedfeeder/configure.zcml
Products/feedfeeder/contenthandler.py
Products/feedfeeder/events.py
Products/feedfeeder/extendeddatetime.py
Products/feedfeeder/setuphandlers.py
Products/feedfeeder/update_locales.sh
Products/feedfeeder/utilities.py
Products/feedfeeder/Extensions/__init__.py
Products/feedfeeder/Extensions/install.py
Products/feedfeeder/browser/__init__.py
Products/feedfeeder/browser/configure.zcml
Products/feedfeeder/browser/feed-folder.pt
Products/feedfeeder/browser/feed-item.pt
Products/feedfeeder/browser/feed.py
Products/feedfeeder/browser/feeditem.py
Products/feedfeeder/browser/viewlets.py
Products/feedfeeder/content/__init__.py
Products/feedfeeder/content/folder.py
Products/feedfeeder/content/item.py
Products/feedfeeder/doc/__init__.py
Products/feedfeeder/doc/extendeddatetime.txt
Products/feedfeeder/doc/feedconsuming.txt
Products/feedfeeder/doc/feedfeeder-integration.txt
Products/feedfeeder/interfaces/__init__.py
Products/feedfeeder/interfaces/consumer.py
Products/feedfeeder/interfaces/container.py
Products/feedfeeder/interfaces/contenthandler.py
Products/feedfeeder/interfaces/folderview.py
Products/feedfeeder/interfaces/item.py
Products/feedfeeder/locales/feedfeeder.pot
Products/feedfeeder/locales/plone.pot
Products/feedfeeder/locales/de/LC_MESSAGES/feedfeeder.mo
Products/feedfeeder/locales/de/LC_MESSAGES/feedfeeder.po
Products/feedfeeder/locales/de/LC_MESSAGES/plone.mo
Products/feedfeeder/locales/de/LC_MESSAGES/plone.po
Products/feedfeeder/locales/es/LC_MESSAGES/feedfeeder.mo
Products/feedfeeder/locales/es/LC_MESSAGES/feedfeeder.po
Products/feedfeeder/locales/es/LC_MESSAGES/plone.mo
Products/feedfeeder/locales/es/LC_MESSAGES/plone.po
Products/feedfeeder/locales/eu/LC_MESSAGES/feedfeeder.mo
Products/feedfeeder/locales/eu/LC_MESSAGES/feedfeeder.po
Products/feedfeeder/locales/eu/LC_MESSAGES/plone.mo
