Metadata-Version: 1.1
Name: Products.feedfeeder
Version: 3.0.0
Summary: Turn external feed entries into content items
Home-page: https://github.com/collective/Products.feedfeeder
Author: Zest Software
Author-email: m.van.rees@zestsoftware.nl
License: GPL
Keywords: feed rss atom
Platform: UNKNOWN
Classifier: Framework :: Plone
Classifier: Framework :: Plone :: 4.3
Classifier: Framework :: Plone :: 5.0
Classifier: Programming Language :: Python
Classifier: Programming Language :: Python :: 2.6
Classifier: Programming Language :: Python :: 2.7
Classifier: Topic :: Software Development :: Libraries :: Python Modules
